nano_wait/__init__.py
nano_wait/__main__.py
nano_wait/cli.py
nano_wait/core.py
nano_wait/nano_wait.py
nano_wait/utils.py
nano_wait/vision.py
nano_wait-3.2.0.dist-info/licenses/LICENSE
nano_wait-3.2.0.dist-info/METADATA
nano_wait-3.2.0.dist-info/WHEEL
nano_wait-3.2.0.dist-info/entry_points.txt
nano_wait-3.2.0.dist-info/top_level.txt
nano_wait-3.2.0.dist-info/RECORD
