Metadata-Version: 2.4
Name: nano_wait
Version: 3.2.0
Summary: Adaptive waiting and computer vision execution engine — replaces time.sleep() with system-aware, vision-driven automation.
Author: Luiz Filipe Seabra de Marco
Author-email: luizfilipeseabra@icloud.com
License: MIT
Keywords: automation,adaptive wait,smart wait,execution engine,gui automation,computer vision,vision mode,ocr,screen automation,rpa,ai automation,pyautogui,selenium alternative,testing,wifi awareness,system context
Classifier: Development Status :: 5 - Production/Stable
Classifier: Intended Audience :: Developers
Classifier: Intended Audience :: Science/Research
Classifier: Topic :: Software Development :: Libraries
Classifier: Topic :: Software Development :: Testing
Classifier: Topic :: Desktop Environment
Classifier: Topic :: Scientific/Engineering :: Artificial Intelligence
Classifier: Topic :: Utilities
Classifier: License :: OSI Approved :: MIT License
Classifier: Programming Language :: Python :: 3
Classifier: Programming Language :: Python :: 3.8
Classifier: Programming Language :: Python :: 3.9
Classifier: Programming Language :: Python :: 3.10
Classifier: Programming Language :: Python :: 3.11
Classifier: Operating System :: OS Independent
Requires-Python: >=3.8
License-File: LICENSE
Requires-Dist: psutil
Requires-Dist: pywifi
Provides-Extra: vision
Requires-Dist: pyautogui; extra == "vision"
Requires-Dist: pytesseract; extra == "vision"
Requires-Dist: pynput; extra == "vision"
Requires-Dist: opencv-python; extra == "vision"
Requires-Dist: numpy; extra == "vision"
Requires-Dist: Pillow; extra == "vision"
Provides-Extra: dev
Requires-Dist: pytest; extra == "dev"
Requires-Dist: pytest-mock; extra == "dev"
Dynamic: author
Dynamic: author-email
Dynamic: classifier
Dynamic: description
Dynamic: description-content-type
Dynamic: keywords
Dynamic: license
Dynamic: license-file
Dynamic: provides-extra
Dynamic: requires-dist
Dynamic: requires-python
Dynamic: summary
